http_browser/__init__.py
http_browser/_browser.py
http_browser/_config.py
http_browser/_httpserver.py
http_browser/_main.py
http_browser-1.1.5.dist-info/METADATA
http_browser-1.1.5.dist-info/WHEEL
http_browser-1.1.5.dist-info/top_level.txt
http_browser-1.1.5.dist-info/RECORD
