Metadata-Version: 2.1
Name: http-browser
Version: 1.1.5
Summary: http_browser
Home-page: UNKNOWN
Author: jiaobenxiaozi
Author-email: 
License: UNKNOWN
Platform: UNKNOWN
Requires-Python: >=3.6
Requires-Dist: DrissionPage
